pytest_cleanslate/__init__.py
pytest_cleanslate/__main__.py
pytest_cleanslate/__version__.py
pytest_cleanslate/plugin.py
pytest_cleanslate/reduce.py
pytest_cleanslate-1.0.6.dist-info/LICENSE
pytest_cleanslate-1.0.6.dist-info/METADATA
pytest_cleanslate-1.0.6.dist-info/WHEEL
pytest_cleanslate-1.0.6.dist-info/entry_points.txt
pytest_cleanslate-1.0.6.dist-info/top_level.txt
pytest_cleanslate-1.0.6.dist-info/RECORD
