Metadata-Version: 2.1
Name: pytest-cleanslate
Version: 1.0.6
Summary: Collects and executes pytest tests separately
Author-email: Juan Altmayer Pizzorno <juan@altmayer.com>
Project-URL: Repository, https://github.com/plasma-umass/pytest_cleanslate
Classifier: Programming Language :: Python :: 3.8
Classifier: Programming Language :: Python :: 3.9
Classifier: Programming Language :: Python :: 3.10
Classifier: Programming Language :: Python :: 3.11
Classifier: Programming Language :: Python :: 3.12
Classifier: License :: OSI Approved :: Apache Software License
Classifier: Operating System :: POSIX :: Linux
Classifier: Operating System :: MacOS :: MacOS X
Requires-Python: >=3.8
License-File: LICENSE
Requires-Dist: pytest
Requires-Dist: py
Requires-Dist: pytest-forked
Requires-Dist: tqdm
